squidient/__init__.py
squidient/cli.py
squidient/configure.py
squidient/definitions.py
squidient/git.py
squidient/init.py
squidient/squidient.py
squidient/squidientmonitor.py
squidient/builds/benchmarkbuild.py
squidient/builds/benchmarkbuilder.py
squidient/builds/build.py
squidient/builds/builder.py
squidient/builds/executablebuild.py
squidient/builds/predefinedbuild.py
squidient/codecoverage/codecoverage.py
squidient/codecoverage/gcovrcodecoverage.py
squidient/codecoverage/intelcodecoverage.py
squidient/compilation/cmakeoptions.py
squidient/compilation/configgenerator.py
squidient/connection/buildlock.py
squidient/connection/job.py
squidient/connection/ssh.py
squidient/connection/sshconfigchecker.py
squidient/data/.squidient-initialized
squidient/data/index.html
squidient/data/alya-config/cmake-alamak.json
squidient/data/alya-config/cmake-chemint.json
squidient/data/alya-config/cmake-clang.json
squidient/data/alya-config/cmake-commdom.json
squidient/data/alya-config/cmake-gnu.json
squidient/data/alya-config/cmake-intel-mn4.json
squidient/data/alya-config/cmake-intel.json
squidient/data/alya-config/cmake-mumps.json
squidient/data/alya-config/cmake-nvhpc.json
squidient/data/alya-config/cmake-pgi.json
squidient/data/alya-config/cmake-talp.json
squidient/data/alya-config/cmake-tubes.json
squidient/data/alya-config/cmake-xl.json
squidient/data/alya-config/gnu.json
squidient/data/alya-config/intel.json
squidient/data/alya-config/pgi.json
squidient/data/alya-config/ple.json
squidient/data/alya-config/xl.json
squidient/data/benchmarks/benchmarks.json
squidient/data/builds/builds-old.json
squidient/data/builds/builds.json
squidient/data/builds/cc.json
squidient/data/builds/defaults.json
squidient/data/builds/predefined-old.json
squidient/data/builds/predefined.json
squidient/data/configurations/projects.json
squidient/data/configurations/systems.json
squidient/data/configurations/tests.json
squidient/data/email/report.html
squidient/data/icons/big.png
squidient-1.2.0.dist-info/METADATA
squidient-1.2.0.dist-info/WHEEL
squidient-1.2.0.dist-info/entry_points.txt
squidient-1.2.0.dist-info/licenses/LICENSE.txt
squidient-1.2.0.dist-info/RECORD
