Metadata-Version: 2.4
Name: squidient
Version: 1.2.0
Summary: CI/CD framework for alya
Project-URL: Homepage, https://alya.gitlab.bsc.es/alya/ci-cd/squidient
Project-URL: Bug Tracker, https://alya.gitlab.bsc.es/alya/ci-cd/squidient/issues
Author-email: Damien Dosimont <damien.dosimont@gmail.com>
License-File: LICENSE.txt
Classifier: License :: OSI Approved :: GNU General Public License v3 or later (GPLv3+)
Classifier: Operating System :: POSIX :: Linux
Classifier: Programming Language :: Python :: 3
Requires-Python: >=3.7
Requires-Dist: importlib-resources; python_version < '3.9'
Requires-Dist: lxml
Requires-Dist: mariasql>=5
Requires-Dist: packaging>=21.3
